<?xml version="1.0" encoding="utf-8"?>
<fontMetrics file="Texture.png">
  <character key="32">
    <x>8</x>
    <y>8</y>
    <width>13</width>
    <height>42</height>
  </character>
  <character key="33">
    <x>29</x>
    <y>8</y>
    <width>6</width>
    <height>42</height>
  </character>
  <character key="34">
    <x>43</x>
    <y>8</y>
    <width>12</width>
    <height>42</height>
  </character>
  <character key="35">
    <x>63</x>
    <y>8</y>
    <width>20</width>
    <height>42</height>
  </character>
  <character key="36">
    <x>91</x>
    <y>8</y>
    <width>16</width>
    <height>42</height>
  </character>
  <character key="37">
    <x>115</x>
    <y>8</y>
    <width>26</width>
    <height>42</height>
  </character>
  <character key="38">
    <x>149</x>
    <y>8</y>
    <width>18</width>
    <height>42</height>
  </character>
  <character key="39">
    <x>175</x>
    <y>8</y>
    <width>5</width>
    <height>42</height>
  </character>
  <character key="40">
    <x>188</x>
    <y>8</y>
    <width>11</width>
    <height>42</height>
  </character>
  <character key="41">
    <x>207</x>
    <y>8</y>
    <width>10</width>
    <height>42</height>
  </character>
  <character key="42">
    <x>225</x>
    <y>8</y>
    <width>16</width>
    <height>42</height>
  </character>
  <character key="43">
    <x>249</x>
    <y>8</y>
    <width>17</width>
    <height>42</height>
  </character>
  <character key="44">
    <x>274</x>
    <y>8</y>
    <width>6</width>
    <height>42</height>
  </character>
  <character key="45">
    <x>288</x>
    <y>8</y>
    <width>10</width>
    <height>42</height>
  </character>
  <character key="46">
    <x>306</x>
    <y>8</y>
    <width>5</width>
    <height>42</height>
  </character>
  <character key="47">
    <x>319</x>
    <y>8</y>
    <width>17</width>
    <height>42</height>
  </character>
  <character key="48">
    <x>8</x>
    <y>58</y>
    <width>16</width>
    <height>42</height>
  </character>
  <character key="49">
    <x>32</x>
    <y>58</y>
    <width>7</width>
    <height>42</height>
  </character>
  <character key="50">
    <x>47</x>
    <y>58</y>
    <width>16</width>
    <height>42</height>
  </character>
  <character key="51">
    <x>71</x>
    <y>58</y>
    <width>16</width>
    <height>42</height>
  </character>
  <character key="52">
    <x>95</x>
    <y>58</y>
    <width>18</width>
    <height>42</height>
  </character>
  <character key="53">
    <x>121</x>
    <y>58</y>
    <width>16</width>
    <height>42</height>
  </character>
  <character key="54">
    <x>145</x>
    <y>58</y>
    <width>16</width>
    <height>42</height>
  </character>
  <character key="55">
    <x>169</x>
    <y>58</y>
    <width>16</width>
    <height>42</height>
  </character>
  <character key="56">
    <x>193</x>
    <y>58</y>
    <width>16</width>
    <height>42</height>
  </character>
  <character key="57">
    <x>217</x>
    <y>58</y>
    <width>16</width>
    <height>42</height>
  </character>
  <character key="58">
    <x>241</x>
    <y>58</y>
    <width>5</width>
    <height>42</height>
  </character>
  <character key="59">
    <x>254</x>
    <y>58</y>
    <width>6</width>
    <height>42</height>
  </character>
  <character key="60">
    <x>268</x>
    <y>58</y>
    <width>12</width>
    <height>42</height>
  </character>
  <character key="61">
    <x>288</x>
    <y>58</y>
    <width>17</width>
    <height>42</height>
  </character>
  <character key="62">
    <x>313</x>
    <y>58</y>
    <width>13</width>
    <height>42</height>
  </character>
  <character key="63">
    <x>334</x>
    <y>58</y>
    <width>15</width>
    <height>42</height>
  </character>
  <character key="64">
    <x>8</x>
    <y>108</y>
    <width>21</width>
    <height>42</height>
  </character>
  <character key="65">
    <x>37</x>
    <y>108</y>
    <width>18</width>
    <height>42</height>
  </character>
  <character key="66">
    <x>63</x>
    <y>108</y>
    <width>16</width>
    <height>42</height>
  </character>
  <character key="67">
    <x>87</x>
    <y>108</y>
    <width>16</width>
    <height>42</height>
  </character>
  <character key="68">
    <x>111</x>
    <y>108</y>
    <width>17</width>
    <height>42</height>
  </character>
  <character key="69">
    <x>136</x>
    <y>108</y>
    <width>14</width>
    <height>42</height>
  </character>
  <character key="70">
    <x>158</x>
    <y>108</y>
    <width>14</width>
    <height>42</height>
  </character>
  <character key="71">
    <x>180</x>
    <y>108</y>
    <width>16</width>
    <height>42</height>
  </character>
  <character key="72">
    <x>204</x>
    <y>108</y>
    <width>17</width>
    <height>42</height>
  </character>
  <character key="73">
    <x>229</x>
    <y>108</y>
    <width>5</width>
    <height>42</height>
  </character>
  <character key="74">
    <x>242</x>
    <y>108</y>
    <width>15</width>
    <height>42</height>
  </character>
  <character key="75">
    <x>265</x>
    <y>108</y>
    <width>17</width>
    <height>42</height>
  </character>
  <character key="76">
    <x>290</x>
    <y>108</y>
    <width>13</width>
    <height>42</height>
  </character>
  <character key="77">
    <x>311</x>
    <y>108</y>
    <width>20</width>
    <height>42</height>
  </character>
  <character key="78">
    <x>339</x>
    <y>108</y>
    <width>17</width>
    <height>42</height>
  </character>
  <character key="79">
    <x>364</x>
    <y>108</y>
    <width>17</width>
    <height>42</height>
  </character>
  <character key="80">
    <x>8</x>
    <y>158</y>
    <width>16</width>
    <height>42</height>
  </character>
  <character key="81">
    <x>32</x>
    <y>158</y>
    <width>19</width>
    <height>42</height>
  </character>
  <character key="82">
    <x>59</x>
    <y>158</y>
    <width>17</width>
    <height>42</height>
  </character>
  <character key="83">
    <x>84</x>
    <y>158</y>
    <width>16</width>
    <height>42</height>
  </character>
  <character key="84">
    <x>108</x>
    <y>158</y>
    <width>16</width>
    <height>42</height>
  </character>
  <character key="85">
    <x>132</x>
    <y>158</y>
    <width>17</width>
    <height>42</height>
  </character>
  <character key="86">
    <x>157</x>
    <y>158</y>
    <width>18</width>
    <height>42</height>
  </character>
  <character key="87">
    <x>183</x>
    <y>158</y>
    <width>25</width>
    <height>42</height>
  </character>
  <character key="88">
    <x>216</x>
    <y>158</y>
    <width>18</width>
    <height>42</height>
  </character>
  <character key="89">
    <x>242</x>
    <y>158</y>
    <width>18</width>
    <height>42</height>
  </character>
  <character key="90">
    <x>268</x>
    <y>158</y>
    <width>15</width>
    <height>42</height>
  </character>
  <character key="91">
    <x>291</x>
    <y>158</y>
    <width>10</width>
    <height>42</height>
  </character>
  <character key="92">
    <x>309</x>
    <y>158</y>
    <width>17</width>
    <height>42</height>
  </character>
  <character key="93">
    <x>334</x>
    <y>158</y>
    <width>9</width>
    <height>42</height>
  </character>
  <character key="94">
    <x>351</x>
    <y>158</y>
    <width>15</width>
    <height>42</height>
  </character>
  <character key="95">
    <x>374</x>
    <y>158</y>
    <width>16</width>
    <height>42</height>
  </character>
  <character key="96">
    <x>8</x>
    <y>208</y>
    <width>10</width>
    <height>42</height>
  </character>
  <character key="97">
    <x>26</x>
    <y>208</y>
    <width>14</width>
    <height>42</height>
  </character>
  <character key="98">
    <x>48</x>
    <y>208</y>
    <width>14</width>
    <height>42</height>
  </character>
  <character key="99">
    <x>70</x>
    <y>208</y>
    <width>14</width>
    <height>42</height>
  </character>
  <character key="100">
    <x>92</x>
    <y>208</y>
    <width>14</width>
    <height>42</height>
  </character>
  <character key="101">
    <x>114</x>
    <y>208</y>
    <width>14</width>
    <height>42</height>
  </character>
  <character key="102">
    <x>136</x>
    <y>208</y>
    <width>11</width>
    <height>42</height>
  </character>
  <character key="103">
    <x>155</x>
    <y>208</y>
    <width>14</width>
    <height>42</height>
  </character>
  <character key="104">
    <x>177</x>
    <y>208</y>
    <width>14</width>
    <height>42</height>
  </character>
  <character key="105">
    <x>199</x>
    <y>208</y>
    <width>6</width>
    <height>42</height>
  </character>
  <character key="106">
    <x>213</x>
    <y>208</y>
    <width>9</width>
    <height>42</height>
  </character>
  <character key="107">
    <x>230</x>
    <y>208</y>
    <width>14</width>
    <height>42</height>
  </character>
  <character key="108">
    <x>252</x>
    <y>208</y>
    <width>6</width>
    <height>42</height>
  </character>
  <character key="109">
    <x>266</x>
    <y>208</y>
    <width>23</width>
    <height>42</height>
  </character>
  <character key="110">
    <x>297</x>
    <y>208</y>
    <width>14</width>
    <height>42</height>
  </character>
  <character key="111">
    <x>319</x>
    <y>208</y>
    <width>14</width>
    <height>42</height>
  </character>
  <character key="112">
    <x>8</x>
    <y>258</y>
    <width>14</width>
    <height>42</height>
  </character>
  <character key="113">
    <x>30</x>
    <y>258</y>
    <width>14</width>
    <height>42</height>
  </character>
  <character key="114">
    <x>52</x>
    <y>258</y>
    <width>14</width>
    <height>42</height>
  </character>
  <character key="115">
    <x>74</x>
    <y>258</y>
    <width>13</width>
    <height>42</height>
  </character>
  <character key="116">
    <x>95</x>
    <y>258</y>
    <width>11</width>
    <height>42</height>
  </character>
  <character key="117">
    <x>114</x>
    <y>258</y>
    <width>14</width>
    <height>42</height>
  </character>
  <character key="118">
    <x>136</x>
    <y>258</y>
    <width>15</width>
    <height>42</height>
  </character>
  <character key="119">
    <x>159</x>
    <y>258</y>
    <width>22</width>
    <height>42</height>
  </character>
  <character key="120">
    <x>189</x>
    <y>258</y>
    <width>15</width>
    <height>42</height>
  </character>
  <character key="121">
    <x>212</x>
    <y>258</y>
    <width>15</width>
    <height>42</height>
  </character>
  <character key="122">
    <x>235</x>
    <y>258</y>
    <width>13</width>
    <height>42</height>
  </character>
  <character key="123">
    <x>256</x>
    <y>258</y>
    <width>13</width>
    <height>42</height>
  </character>
  <character key="124">
    <x>277</x>
    <y>258</y>
    <width>5</width>
    <height>42</height>
  </character>
  <character key="125">
    <x>290</x>
    <y>258</y>
    <width>13</width>
    <height>42</height>
  </character>
  <character key="126">
    <x>311</x>
    <y>258</y>
    <width>16</width>
    <height>42</height>
  </character>
  <character key="127">
    <x>335</x>
    <y>258</y>
    <width>16</width>
    <height>42</height>
  </character>
</fontMetrics>